wired_table_rec/__init__.py
wired_table_rec/main.py
wired_table_rec/table_recover.py
wired_table_rec/table_structure_cycle_center_net.py
wired_table_rec/table_structure_unet.py
wired_table_rec/utils/__init__.py
wired_table_rec/utils/download_model.py
wired_table_rec/utils/logger.py
wired_table_rec/utils/utils.py
wired_table_rec/utils/utils_table_line_rec.py
wired_table_rec/utils/utils_table_recover.py
wired_table_rec-1.2.0.dist-info/LICENSE
wired_table_rec-1.2.0.dist-info/METADATA
wired_table_rec-1.2.0.dist-info/WHEEL
wired_table_rec-1.2.0.dist-info/entry_points.txt
wired_table_rec-1.2.0.dist-info/top_level.txt
wired_table_rec-1.2.0.dist-info/RECORD
