Metadata-Version: 2.1
Name: wired-table-rec
Version: 1.2.0
Summary: Wired Table Recognition
Home-page: https://github.com/RapidAI/TableStructureRec
Author: SWHL
Author-email: liekkaskono@163.com
License: Apache-2.0
Keywords: tsr,ocr,table-recognition
Platform: Any
Classifier: Programming Language :: Python :: 3.6
Classifier: Programming Language :: Python :: 3.7
Classifier: Programming Language :: Python :: 3.8
Classifier: Programming Language :: Python :: 3.9
Classifier: Programming Language :: Python :: 3.10
Classifier: Programming Language :: Python :: 3.11
Classifier: Programming Language :: Python :: 3.12
Requires-Python: >=3.6,<3.13
License-File: LICENSE
Requires-Dist: numpy>=1.21.6
Requires-Dist: onnxruntime>=1.14.1
Requires-Dist: opencv-python
Requires-Dist: scipy
Requires-Dist: scikit-image
Requires-Dist: Shapely
Requires-Dist: requests
Requires-Dist: tqdm
